{
  "frames": {
    "0": { "frame": { "x": 48, "y": 6, "w": 16, "h": 3 } },
    "1": { "frame": { "x": 34, "y": 3, "w": 12, "h": 10 } },
    "2": { "frame": { "x": 23, "y": 2, "w": 1, "h": 13 } },
    "3": { "frame": { "x": 34, "y": 3, "w": 12, "h": 10 } },
    "4": { "frame": { "x": 48, "y": 6, "w": 16, "h": 3 } },
    "5": { "frame": { "x": 66, "y": 4, "w": 12, "h": 9 } },
    "6": { "frame": { "x": 87, "y": 2, "w": 1, "h": 12 } },
    "7": { "frame": { "x": 66, "y": 4, "w": 12, "h": 9 } }
  },
  "meta": {
    "image": "awp.png",
    "size": { "w": 128, "h": 16 },
    "scale": "1.2"
  }
}
